netdef/__init__.py
netdef/__main__.py
netdef/application_main_template.py
netdef/service.py
netdef/systemd_service.py
netdef/testutils.py
netdef/utils.py
netdef/windows_service.py
netdef/Controllers/BaseAsyncController.py
netdef/Controllers/BaseAsyncParallelController.py
netdef/Controllers/BaseController.py
netdef/Controllers/CommTestController.py
netdef/Controllers/ConcurrentWebRequestController.py
netdef/Controllers/Controllers.py
netdef/Controllers/CrontabController.py
netdef/Controllers/InfluxDBLoggerController.py
netdef/Controllers/InternalController.py
netdef/Controllers/MQTTDataMessageController.py
netdef/Controllers/ModbusClientController.py
netdef/Controllers/ModbusServerController.py
netdef/Controllers/NewControllerTemplate.py
netdef/Controllers/OPCUAClientController.py
netdef/Controllers/OPCUAServerController.py
netdef/Controllers/RESTJsonController.py
netdef/Controllers/SubprocessController.py
netdef/Controllers/SystemMonitorController.py
netdef/Controllers/XmlRpcController.py
netdef/Controllers/ZmqDataAccessController.py
netdef/Controllers/__init__.py
netdef/Controllers/ping/__init__.py
netdef/Controllers/ping/ping.py
netdef/Engines/BaseEngine.py
netdef/Engines/NginxWebGuiReverseProxy.py
netdef/Engines/ThreadedEngine.py
netdef/Engines/ThreadedWebGuiEngine.py
netdef/Engines/__init__.py
netdef/Engines/utils.py
netdef/Engines/expression/Collector.py
netdef/Engines/expression/Expression.py
netdef/Engines/expression/__init__.py
netdef/Engines/templates/autoupgrade.html
netdef/Engines/templates/debugging.html
netdef/Engines/templates/docs.html
netdef/Engines/templates/home.html
netdef/Engines/templates/tools.html
netdef/Engines/templates/admin/fileedit.html
netdef/Engines/templates/admin/filelist.html
netdef/Engines/templates/admin/index.html
netdef/Engines/templates/home/home.html
netdef/Engines/templates/security/builtin_controllers.html
netdef/Engines/templates/security/certificates.html
netdef/Engines/templates/security/webadmin.html
netdef-1.0.7.dist-info/AUTHORS.rst
netdef-1.0.7.dist-info/COPYING
netdef-1.0.7.dist-info/METADATA
netdef-1.0.7.dist-info/WHEEL
netdef-1.0.7.dist-info/entry_points.txt
netdef-1.0.7.dist-info/top_level.txt
netdef-1.0.7.dist-info/RECORD
