Metadata-Version: 2.1
Name: netdef
Version: 1.0.7
Summary: An application framework with built-in drivers (Controllers), data holders (Sources) and config parsers (Rules). Also includes a web interface for configuration and troubleshooting.
Home-page: https://gitlab.com/fholmer/netdef
Author: Frode Holmer
Author-email: fholmer+netdef@gmail.com
License: GNU Lesser General Public License v3 or later
Project-URL: Source Code, https://gitlab.com/fholmer/netdef
Project-URL: Documentation, https://netdef.readthedocs.io/en/latest/
Keywords: Application Framework Networking Monitoring
Platform: UNKNOWN
Classifier: Development Status :: 5 - Production/Stable
Classifier: Environment :: Console
Classifier: Environment :: Web Environment
Classifier: Intended Audience :: Developers
Classifier: License :: OSI Approved :: GNU Lesser General Public License v3 or later (LGPLv3+)
Classifier: Programming Language :: Python :: 3
Classifier: Programming Language :: Python :: 3.5
Classifier: Programming Language :: Python :: 3.6
Classifier: Programming Language :: Python :: 3.7
Classifier: Operating System :: POSIX :: Linux
Classifier: Operating System :: Microsoft :: Windows
Classifier: Topic :: Software Development :: Libraries :: Application Frameworks
Classifier: Topic :: System :: Networking :: Monitoring
Classifier: Topic :: System :: Monitoring
Requires-Python: >=3.5
Requires-Dist: Flask
Requires-Dist: Flask-Admin
Requires-Dist: Flask-BasicAuth
Requires-Dist: Flask-Login
Requires-Dist: Jinja2
Requires-Dist: Werkzeug
Requires-Dist: psutil
Provides-Extra: full
Requires-Dist: Flask ; extra == 'full'
Requires-Dist: Flask-Admin ; extra == 'full'
Requires-Dist: Flask-BasicAuth ; extra == 'full'
Requires-Dist: Flask-Login ; extra == 'full'
Requires-Dist: Jinja2 ; extra == 'full'
Requires-Dist: PyYAML ; extra == 'full'
Requires-Dist: Werkzeug ; extra == 'full'
Requires-Dist: aiohttp ; extra == 'full'
Requires-Dist: crontab ; extra == 'full'
Requires-Dist: cryptography ; extra == 'full'
Requires-Dist: freeopcua ; extra == 'full'
Requires-Dist: influxdb ; extra == 'full'
Requires-Dist: paho-mqtt ; extra == 'full'
Requires-Dist: psutil ; extra == 'full'
Requires-Dist: pymodbus ; extra == 'full'
Requires-Dist: pytz ; extra == 'full'
Requires-Dist: pyzmq ; extra == 'full'
Requires-Dist: schema ; extra == 'full'
Requires-Dist: six (==1.11.0) ; extra == 'full'
Requires-Dist: waitress ; extra == 'full'
Requires-Dist: pywin32 ; (sys_platform == "win32") and extra == 'full'
Provides-Extra: windows-service
Requires-Dist: pywin32 ; extra == 'windows-service'
